gludb/__init__.py
gludb/backup.py
gludb/config.py
gludb/data.py
gludb/simple.py
gludb/utils.py
gludb/versioning.py
gludb/backends/__init__.py
gludb/backends/dynamodb.py
gludb/backends/gcd.py
gludb/backends/mongodb.py
gludb/backends/postgresql.py
gludb/backends/sqlite.py
gludb-0.2.0.dist-info/DESCRIPTION.rst
gludb-0.2.0.dist-info/METADATA
gludb-0.2.0.dist-info/RECORD
gludb-0.2.0.dist-info/WHEEL
gludb-0.2.0.dist-info/metadata.json
gludb-0.2.0.dist-info/top_level.txt
