Metadata-Version: 2.0
Name: gludb
Version: 0.2.0
Summary: A simple database wrapper
Home-page: https://github.com/memphis-iis/GLUDB
Author: University of Memphis Institute for Intelligent Systems
Author-email: cnkelly@memphis.edu
License: Apache Version 2.0
Keywords: database versioning backupsqlite dynamodb cloud datastore mongodb
Platform: UNKNOWN
Classifier: Development Status :: 4 - Beta
Classifier: Intended Audience :: Developers
Classifier: Topic :: Database
Classifier: Topic :: Software Development :: Libraries
Classifier: Topic :: System :: Archiving :: Backup
Classifier: License :: OSI Approved :: Apache Software License
Classifier: Programming Language :: Python :: 2
Classifier: Programming Language :: Python :: 2.7
Classifier: Programming Language :: Python :: 3
Classifier: Programming Language :: Python :: 3.2
Classifier: Programming Language :: Python :: 3.3
Classifier: Programming Language :: Python :: 3.4
Classifier: Programming Language :: Python :: 3.5
Requires-Dist: json-delta (>=1.1.3)
Provides-Extra: backups
Requires-Dist: boto; extra == 'backups'
Provides-Extra: dev
Provides-Extra: dynamodb
Requires-Dist: boto; extra == 'dynamodb'
Provides-Extra: gcd
Requires-Dist: googledatastore; extra == 'gcd'
Provides-Extra: mongodb
Requires-Dist: pymongo; extra == 'mongodb'
Provides-Extra: postgresql
Requires-Dist: psycopg2; extra == 'postgresql'
Provides-Extra: test
Requires-Dist: coverage; extra == 'test'
Requires-Dist: nose; extra == 'test'
Requires-Dist: tornado; extra == 'test'
